rpwd/__init__.py
rpwd-0.1.2.dist-info/LICENSE
rpwd-0.1.2.dist-info/METADATA
rpwd-0.1.2.dist-info/WHEEL
rpwd-0.1.2.dist-info/entry_points.txt
rpwd-0.1.2.dist-info/top_level.txt
rpwd-0.1.2.dist-info/RECORD
