Metadata-Version: 2.1
Name: rpwd
Version: 0.1.2
Summary: Rename Photos With Date
Home-page: https://github.com/AndyM129/rename_photos_with_date
Author: Andy Meng
Author-email: andy_m129@163.com
License: GNU General Public License v3.0
Platform: UNKNOWN
Requires-Python: >=3.9
License-File: LICENSE
Requires-Dist: colorama
Requires-Dist: exifread
